pyduplicate/__init__.py
pyduplicate/data/__init__.py
pyduplicate/data/const.py
pyduplicate/data/from_list.py
pyduplicate/data/utils.py
pyduplicate/database/__init__.py
pyduplicate/database/from_mysql.py
pyduplicate/database/from_psql.py
pyduplicate/database/utils.py
python_duplicate-1.0.4.dist-info/LICENSE
python_duplicate-1.0.4.dist-info/METADATA
python_duplicate-1.0.4.dist-info/WHEEL
python_duplicate-1.0.4.dist-info/top_level.txt
python_duplicate-1.0.4.dist-info/RECORD
