Metadata-Version: 2.1
Name: python-duplicate
Version: 1.0.4
Summary: Handle duplicate in python
Home-page: https://github.com/Clement-O/python-duplicate
Author: Clément Omont--Agnes
Author-email: omont.clement@gmail.com
License: MIT
Project-URL: Documentation, https://python-duplicate.readthedocs.io/en/latest/
Project-URL: Source, https://github.com/Clement-O/python-duplicate
Platform: UNKNOWN
Requires-Dist: psycopg2-binary
Requires-Dist: PyMySQL
